# 001

## 是什么？

想做什么？

| Index | Opcode        | Index | Opcode     | Index | Opcode            | Index | Opcode           |
| ----- | ------------- | ----- | ---------- | ----- | ----------------- | ----- | ---------------- |
| `0`   | `nop`         | `64`  | `lstore_1` | `128` | `ior`             | `192` | `checkcast`      |
| `1`   | `aconst_null` | `65`  | `lstore_2` | `129` | `lor`             | `193` | `instanceof`     |
| `2`   | `iconst_m1`   | `66`  | `lstore_3` | `130` | `ixor`            | `194` | `monitorenter`   |
| `3`   | `iconst_0`    | `67`  | `fstore_0` | `131` | `lxor`            | `195` | `monitorexit`    |
| `4`   | `iconst_1`    | `68`  | `fstore_1` | `132` | `iinc`            | `196` | `wide`           |
| `5`   | `iconst_2`    | `69`  | `fstore_2` | `133` | `i2l`             | `197` | `multianewarray` |
| `6`   | `iconst_3`    | `70`  | `fstore_3` | `134` | `i2f`             | `198` | `ifnull`         |
| `7`   | `iconst_4`    | `71`  | `dstore_0` | `135` | `i2d`             | `199` | `ifnonnull`      |
| `8`   | `iconst_5`    | `72`  | `dstore_1` | `136` | `l2i`             | `200` | `goto_w`         |
| `9`   | `lconst_0`    | `73`  | `dstore_2` | `137` | `l2f`             | `201` | `jsr_w`          |
| `10`  | `lconst_1`    | `74`  | `dstore_3` | `138` | `l2d`             | `202` | `breakpoint`     |
| `11`  | `fconst_0`    | `75`  | `astore_0` | `139` | `f2i`             | `203` |                  |
| `12`  | `fconst_1`    | `76`  | `astore_1` | `140` | `f2l`             | `204` |                  |
| `13`  | `fconst_2`    | `77`  | `astore_2` | `141` | `f2d`             | `205` |                  |
| `14`  | `dconst_0`    | `78`  | `astore_3` | `142` | `d2i`             | `206` |                  |
| `15`  | `dconst_1`    | `79`  | `iastore`  | `143` | `d2l`             | `207` |                  |
| `16`  | `bipush`      | `80`  | `lastore`  | `144` | `d2f`             | `208` |                  |
| `17`  | `sipush`      | `81`  | `fastore`  | `145` | `i2b`             | `209` |                  |
| `18`  | `ldc`         | `82`  | `dastore`  | `146` | `i2c`             | `210` |                  |
| `19`  | `ldc_w`       | `83`  | `aastore`  | `147` | `i2s`             | `211` |                  |
| `20`  | `ldc2_w`      | `84`  | `bastore`  | `148` | `lcmp`            | `212` |                  |
| `21`  | `iload`       | `85`  | `castore`  | `149` | `fcmpl`           | `213` |                  |
| `22`  | `lload`       | `86`  | `sastore`  | `150` | `fcmpg`           | `214` |                  |
| `23`  | `fload`       | `87`  | `pop`      | `151` | `dcmpl`           | `215` |                  |
| `24`  | `dload`       | `88`  | `pop2`     | `152` | `dcmpg`           | `216` |                  |
| `25`  | `aload`       | `89`  | `dup`      | `153` | `ifeq`            | `217` |                  |
| `26`  | `iload_0`     | `90`  | `dup_x1`   | `154` | `ifne`            | `218` |                  |
| `27`  | `iload_1`     | `91`  | `dup_x2`   | `155` | `iflt`            | `219` |                  |
| `28`  | `iload_2`     | `92`  | `dup2`     | `156` | `ifge`            | `220` |                  |
| `29`  | `iload_3`     | `93`  | `dup2_x1`  | `157` | `ifgt`            | `221` |                  |
| `30`  | `lload_0`     | `94`  | `dup2_x2`  | `158` | `ifle`            | `222` |                  |
| `31`  | `lload_1`     | `95`  | `swap`     | `159` | `if_icmpeq`       | `223` |                  |
| `32`  | `lload_2`     | `96`  | `iadd`     | `160` | `if_icmpne`       | `224` |                  |
| `33`  | `lload_3`     | `97`  | `ladd`     | `161` | `if_icmplt`       | `225` |                  |
| `34`  | `fload_0`     | `98`  | `fadd`     | `162` | `if_icmpge`       | `226` |                  |
| `35`  | `fload_1`     | `99`  | `dadd`     | `163` | `if_icmpgt`       | `227` |                  |
| `36`  | `fload_2`     | `100` | `isub`     | `164` | `if_icmple`       | `228` |                  |
| `37`  | `fload_3`     | `101` | `lsub`     | `165` | `if_acmpeq`       | `229` |                  |
| `38`  | `dload_0`     | `102` | `fsub`     | `166` | `if_acmpne`       | `230` |                  |
| `39`  | `dload_1`     | `103` | `dsub`     | `167` | `goto`            | `231` |                  |
| `40`  | `dload_2`     | `104` | `imul`     | `168` | `jsr`             | `232` |                  |
| `41`  | `dload_3`     | `105` | `lmul`     | `169` | `ret`             | `233` |                  |
| `42`  | `aload_0`     | `106` | `fmul`     | `170` | `tableswitch`     | `234` |                  |
| `43`  | `aload_1`     | `107` | `dmul`     | `171` | `lookupswitch`    | `235` |                  |
| `44`  | `aload_2`     | `108` | `idiv`     | `172` | `ireturn`         | `236` |                  |
| `45`  | `aload_3`     | `109` | `ldiv`     | `173` | `lreturn`         | `237` |                  |
| `46`  | `iaload`      | `110` | `fdiv`     | `174` | `freturn`         | `238` |                  |
| `47`  | `laload`      | `111` | `ddiv`     | `175` | `dreturn`         | `239` |                  |
| `48`  | `faload`      | `112` | `irem`     | `176` | `atreturn`        | `240` |                  |
| `49`  | `daload`      | `113` | `lrem`     | `177` | `return`          | `241` |                  |
| `50`  | `aaload`      | `114` | `frem`     | `178` | `getstaic`        | `242` |                  |
| `51`  | `baload`      | `115` | `drem`     | `179` | `putstatic`       | `243` |                  |
| `52`  | `caload`      | `116` | `ineg`     | `180` | `getfield`        | `244` |                  |
| `53`  | `saload`      | `117` | `lneg`     | `181` | `putfield`        | `245` |                  |
| `54`  | `istore`      | `118` | `fneg`     | `182` | `invokevirtual`   | `246` |                  |
| `55`  | `lstore`      | `119` | `dneg`     | `183` | `invokespecial`   | `247` |                  |
| `56`  | `fstore`      | `120` | `ishl`     | `184` | `invokestatic`    | `248` |                  |
| `57`  | `dstore`      | `121` | `lshl`     | `185` | `invokeinterface` | `249` |                  |
| `58`  | `astore`      | `122` | `ishr`     | `186` | `invokedynamic`   | `250` |                  |
| `59`  | `istore_0`    | `123` | `lshr`     | `187` | `new`             | `251` |                  |
| `60`  | `istore_1`    | `124` | `iushr`    | `188` | `newarray`        | `252` |                  |
| `61`  | `istore_2`    | `125` | `lushr`    | `189` | `anewarray`       | `253` |                  |
| `62`  | `istore_3`    | `126` | `iand`     | `190` | `arraylength`     | `254` | `impdep1`        |
| `63`  | `lstore_0`    | `127` | `land`     | `191` | `athrow`          | `255` | `impdep2`        |



## 从何处来

> 作者有话说：我们讨论的主角是opcode，在讲述opcode的具体内容之前，我们希望能够在一个比opcode更大的视野下去看待opcode。而是像水流一样，它是有源头的。

我们的切入视角是一个`.java`文件，

- (1) 一个`.java`文件，经过Java Compiler编译之后，会生成一个`.class`文件；
- (2) 在`.class`文件中，包含了Java bytecode；
- (3) 这些Java bytecode可以被Java Virtual Machine (JVM)理解和执行。

A **Java class file** is a file (with the `.class` filename extension) containing Java bytecode that can be executed on the Java Virtual Machine (JVM). A **Java class file** is usually produced by a Java compiler from Java programming language source files (`.java` files). -- [Wikipedia:Java class file](https://en.wikipedia.org/wiki/Java_class_file)

<hr/>

作者有话说：另外，需要注意的一点是：JVM懂的是Java bytecode，但并不懂Java programming language。Java bytecode和Java programming language是两个有关系，但并不相同的事物。在`.java`文件中，是使用Java programming language编写的代码，它是一种文本格式的文件；而在`.class`文件中，包含的Java bytecode，它是一种二进制格式的文件。
  
The Java Virtual Machine knows nothing of the **Java programming language**, only of a particular binary format, the `class` file format. A `class` file contains **Java Virtual Machine instructions** (or **bytecodes**) and a symbol table, as well as other ancillary information. -- 《The Java Virtual Machine Specification Java SE 12 Edition》 page2

<hr/>

对于一个`.class`文件来说，虽然是一个二进制的文件，但它的存储内容也并不是杂乱无章的，而是遵循一定的存储结构的。换句话说，`.class`文件包含了bytecode，而bytecode是遵循`ClassFile`格式进行存储的。

A `class` file consists of a single `ClassFile` structure -- 《The Java Virtual Machine Specification Java SE 12 Edition》 page72:

```txt
ClassFile {
    u4 magic_number;
    u2 minor_version;
    u2 major_version;
    u2 constant_pool_count;
    cp_info constant_pool[constant_pool_count-1];
    u2 access_flags;
    u2 this_class;
    u2 super_class;
    u2 interfaces_count;
    u2 interfaces[interfaces_count];
    u2 fields_count;
    field_info fields[fields_count];
    u2 methods_count;
    method_info methods[methods_count];
    u2 attributes_count;
    attribute_info attributes[attributes_count];
}
```

There are 10 basic sections to the **Java Class File structure**:

- **Magic Number**: 0xCAFEBABE
- **Version of Class File Format**: the minor and major versions of the class file
- **Constant Pool**: Pool of constants for the class
- **Access Flags**: for example whether the class is abstract, static, etc.
- **This Class**: The name of the current class
- **Super Class**: The name of the super class
- **Interfaces**: Any interfaces in the class
- **Fields**: Any fields in the class
- **Methods**: Any methods in the class
- **Attributes**: Any attributes of the class (for example the name of the sourcefile, etc.)



要讲述Code属性位于什么位置：位于method的Code属性里。

## 周围环境

有操作数栈、local variable、常量池、堆

就像动词+宾主->结果

方法（参数）->返回值。

**Java bytecode** is the instruction set of the Java virtual machine (JVM).

The JVM is both a **stack machine** and a **register machine**. Each frame for a method call has an "**operand stack**" and an array of "**local variables**". **The operand stack** is used for operands to computations and for receiving the return value of a called method, while **local variables** serve the same purpose as registers and are also used to pass method arguments. The maximum size of **the operand stack** and **local variable array**, computed by the compiler, is part of the attributes of each method. Each can be independently sized from `0` to `65535` values, where each value is 32 bits. long and double types, which are 64 bits, take up two consecutive(连续的) local variables (which need not be 64-bit aligned in the local variables array) or one value in the operand stack (but are counted as two units in the depth of the stack).

lsieun-utils:

```bash
git clone https://github.com/lsieun/lsieun-utils
```

程序配置文件的讲解`config.properties`

> 因为别人并不知道你的程序是如何写的，你要给大家讲清楚，到底是一个怎么样的思路。
> 找到一个class文件的bytecode，这些bytecode当中包含了各个成员（或是字段，或是方法），我们找到其中一个方法进行分析，分析其中的opcode。  
> 第一，是不是jar。classfile.source.use.jar  
> 第二，具体的Jar文件的路径信息 和 .class文件的路径信息。  
> 第三，classfile内容读取的目标：ClassFile、Field、Method、Attribute  
> 第四，classfile读取目标的传入参数

## 小结

每一章，都要有小结。

## 参考

- [Java class file](https://en.wikipedia.org/wiki/Java_class_file)
- [Java bytecode](https://en.wikipedia.org/wiki/Java_bytecode)

