# Opcode Fields

<!-- TOC -->

- [1. ClassFile fields](#1-classfile-fields)
- [2. non-static field](#2-non-static-field)
  - [2.1. getfield](#21-getfield)
  - [2.2. putfield](#22-putfield)
- [3. static field](#3-static-field)
  - [3.1. getstatic](#31-getstatic)
  - [3.2. putstatic](#32-putstatic)
- [4. Summing-up](#4-summing-up)
- [5. Extension: non-static data initialization](#5-extension-non-static-data-initialization)
  - [5.1. Automation Initialization](#51-automation-initialization)
  - [5.2. Specifying Initialization](#52-specifying-initialization)
  - [5.3. Constructor Initialization](#53-constructor-initialization)
- [6. Extension: static data initialization](#6-extension-static-data-initialization)
  - [6.1. static Automation Initialization](#61-static-automation-initialization)
  - [6.2. static Specifying Initialization](#62-static-specifying-initialization)
  - [6.3. Explicit static initialization](#63-explicit-static-initialization)
- [7. Extension: static final data initialization](#7-extension-static-final-data-initialization)
  - [7.1. static final primitive data](#71-static-final-primitive-data)
  - [7.2. static final Object Type](#72-static-final-object-type)
- [8. Extension: Order of Initialization](#8-extension-order-of-initialization)

<!-- /TOC -->

**Fields**. These instructions read or write the value of a field. `GETFIELD owner name desc` pops an object reference, and pushes the value of its `name` field. `PUTFIELD owner name desc` pops a value and an object reference, and stores this value in its `name` field. In both cases the object must be of type `owner`, and its field must be of type `desc`. `GETSTATIC` and `PUTSTATIC` are similar instructions, but for `static` fields.

注意：这里讲Fields，重点并不是讲“如何定义Fields”，而是讲“如何使用Fields”。“如何定义Fields”是属于`ClassFile`结构的内容，而“如何使用Fields”是属于`opcode`的内容。

```java
public class HelloWorld {
    private int value; // (0)这里是定义字段， Definition

    public int getValue() {
        return this.value; // (1)这里是使用字段，获取字段的值
    }

    public void setValue(int value) {
        this.value = value; // (2)这里也是使用字段，设置字段的值
    }
}
```

## 1. ClassFile fields

```txt
ClassFile {
    u4 magic_number;
    u2 minor_version;
    u2 major_version;
    u2 constant_pool_count;
    cp_info constant_pool[constant_pool_count-1];
    u2 access_flags;
    u2 this_class;
    u2 super_class;
    u2 interfaces_count;
    u2 interfaces[interfaces_count];
    u2 fields_count;
    field_info fields[fields_count];
    u2 methods_count;
    method_info methods[methods_count];
    u2 attributes_count;
    attribute_info attributes[attributes_count];
}
```

## 2. non-static field

### 2.1. getfield

学习目标：

- `getfield`

示例代码：

```java
public class HelloWorld {
    public int value;

    public void testSimple() {
        int i = this.value;
    }
}
```

输出结果：

```txt
ConstantPool {
    |001| CONSTANT_Methodref {Value='java/lang/Object.<init>:()V', HexCode='0A00040012'}
    |002| CONSTANT_Fieldref {Value='lsieun/sample/HelloWorld.value:I', HexCode='0900030013'}
    ......

code='2AB400023CB1'
    0: aload_0         // 2A
    1: getfield 2      // B40002
    4: istore_1        // 3C
    5: return          // B1


LocalVariableTable:
index  start_pc  length  name_and_type
    0         0       6  this:Llsieun/sample/HelloWorld;
    1         5       1  i:I
```

### 2.2. putfield

学习目标：

- `putfield`

示例代码：

```java
public class HelloWorld {
    public int value;

    public void testSimple() {
        this.value = 0;
    }
}
```

输出结果：

```txt
ConstantPool {
    |002| CONSTANT_Fieldref {Value='lsieun/sample/HelloWorld.value:I', HexCode='0900030012'}
    ......

code='2A03B50002B1'
    0: aload_0         // 2A
    1: iconst_0        // 03
    2: putfield 2      // B50002
    5: return          // B1


LocalVariableTable:
index  start_pc  length  name_and_type
    0         0       6  this:Llsieun/sample/HelloWorld;
```

## 3. static field

### 3.1. getstatic

学习目标：

- `getstatic`

示例代码：

```java
public class HelloWorld {
    public static int staticValue;

    public void testSimple() {
        int i = HelloWorld.staticValue;
    }
}
```

输出结果（一）：

```txt
ConstantPool {
    |001| CONSTANT_Methodref {Value='java/lang/Object.<init>:()V', HexCode='0A00040012'}
    |002| CONSTANT_Fieldref {Value='lsieun/sample/HelloWorld.staticValue:I', HexCode='0900030013'}
    ......

code='B200023CB1'
    0: getstatic 2     // B20002
    3: istore_1        // 3C
    4: return          // B1


LocalVariableTable:
index  start_pc  length  name_and_type
    0         0       5  this:Llsieun/sample/HelloWorld;
    1         4       1  i:I
```

### 3.2. putstatic

学习目标：

- `putstatic`

示例代码：

```java
public class HelloWorld {
    public static int staticValue;

    public void testSimple() {
        HelloWorld.staticValue = 1;
    }
}
```

输出结果：

```txt
ConstantPool {
    |002| CONSTANT_Fieldref {Value='lsieun/sample/HelloWorld.staticValue:I', HexCode='0900030012'}
    ......

code='04B30002B1'
    0: iconst_1        // 04
    1: putstatic 2     // B30002
    4: return          // B1


LocalVariableTable:
index  start_pc  length  name_and_type
    0         0       5  this:Llsieun/sample/HelloWorld;
```



## 4. Summing-up

知识总结

| opcode | mnemonic symbol | meaning |
| ------ | --------------- | ------- |
| `178`  | `getstatic`     |         |
| `179`  | `putstatic`     |         |
| `180`  | `getfield`      |         |
| `181`  | `putfield`      |         |

## 5. Extension: non-static data initialization

### 5.1. Automation Initialization

If a **primitive** is a field in a class, each **primitive** field of a class is guaranteed to get an initial value. Here’s a program that verifies this, and shows the values:

```java
public class HelloWorld {
    boolean t;
    char c;
    byte b;
    short s;
    int i;
    long l;
    float f;
    double d;
    HelloWorld reference;

    void printInitialValues() {
        System.out.println("Data type    Initial value");
        System.out.println("boolean      " + t);
        System.out.println("char         [" + c + "]");
        System.out.println("byte         " + b);
        System.out.println("short        " + s);
        System.out.println("int          " + i);
        System.out.println("long         " + l);
        System.out.println("float        " + f);
        System.out.println("double       " + d);
        System.out.println("reference    " + reference);
    }

    public static void main(String[] args) {
        HelloWorld instance = new HelloWorld();
        instance.printInitialValues();
    }
}
```

`main`方法输出结果：

```txt
Data type    Initial value
boolean      false
char         [ ]
byte         0
short        0
int          0
long         0
float        0.0
double       0.0
reference    null
```

You can see that even though the values are not specified, they automatically get initialized (the `char` value is a **zero**, which prints as a **space**). So at least there’s no threat of working with uninitialized variables.

When you define an **object reference** inside a class without initializing it to a new object, that reference is given a special value of `null`.

`<init>:()V`的输出结果：

```txt
ConstantPool {
    |001| CONSTANT_Methodref {Value='java/lang/Object.<init>:()V', HexCode='0A00260047'}
    ......

code='2AB70001B1'
    0: aload_0         // 2A
    1: invokespecial 1 // B70001
    4: return          // B1


LocalVariableTable:
index  start_pc  length  name_and_type
    0         0       5  this:Llsieun/sample/HelloWorld;
```


Create a class containing an uninitialized `String` reference. Demonstrate that this reference is initialized by Java to `null`.

```java
public class HelloWorld {
    //关注点：我们并没有在Constructor中对value进行赋值，它默认成为null值。
    private String value;

    public String getValue() {
        return value;
    }

    public static void main(String[] args) {
        HelloWorld instance = new HelloWorld();
        System.out.println(instance.getValue());
    }
}
```

Create a class with a `String` field that is initialized at the point of definition, and another one that is initialized by the constructor. What is the difference between the two approaches?

```java
public class HelloWorld {
    public String strFirst = "Hello";
    public String strSecond;

    public HelloWorld() {
        this.strSecond = "World";
    }

    public static void main(String[] args) {
        HelloWorld instance = new HelloWorld();
        System.out.println(instance.strFirst);
        System.out.println(instance.strSecond);
    }
}
```

目标方法：`<init>:()V`

输出结果：

```txt
ConstantPool {
    |001| CONSTANT_Methodref {Value='java/lang/Object.<init>:()V', HexCode='0A000A001C'}
    |002| CONSTANT_String {Value='Hello', HexCode='08001D'}
    |003| CONSTANT_Fieldref {Value='lsieun/sample/HelloWorld.strFirst:Ljava/lang/String;', HexCode='090006001E'}
    |004| CONSTANT_String {Value='World', HexCode='08001F'}
    |005| CONSTANT_Fieldref {Value='lsieun/sample/HelloWorld.strSecond:Ljava/lang/String;', HexCode='0900060020'}

code='2AB700012A1202B500032A1204B50005B1'
    0: aload_0         // 2A
    1: invokespecial 1 // B70001
    4: aload_0         // 2A
    5: ldc 2           // 1202
    7: putfield 3      // B50003
   10: aload_0         // 2A
   11: ldc 4           // 1204
   13: putfield 5      // B50005
   16: return          // B1


LocalVariableTable:
index  start_pc  length  name_and_type
    0         0      17  this:Llsieun/sample/HelloWorld;
```

### 5.2. Specifying Initialization

What happens if you want to give a variable an initial value? One direct way to do this is simply to assign the value at the point you define the variable in the class. Here the field definitions in class `HelloWorld` are changed to provide initial values:

```java
public class HelloWorld {
    boolean t = true;
    char c = 'x';
    byte b = 47;
    short s = 0xff;
    int i = 999;
    long l = 1;
    float f = 3.14f;
    double d = 3.14159;
    Object reference = new Object();

    void printInitialValues() {
        System.out.println("Data type    Initial value");
        System.out.println("boolean      " + t);
        System.out.println("char         [" + c + "]");
        System.out.println("byte         " + b);
        System.out.println("short        " + s);
        System.out.println("int          " + i);
        System.out.println("long         " + l);
        System.out.println("float        " + f);
        System.out.println("double       " + d);
        System.out.println("reference    " + reference);
    }

    public static void main(String[] args) {
        HelloWorld instance = new HelloWorld();
        instance.printInitialValues();
    }
}
```

`main`输出结果：

```txt
Data type    Initial value
boolean      true
char         [x]
byte         47
short        255
int          999
long         1
float        3.14
double       3.14159
reference    java.lang.Object@7f31245a
```

`<init>:()V`输出结果：

```txt
ConstantPool {
    |001| CONSTANT_Methodref {Value='java/lang/Object.<init>:()V', HexCode='0A000D004B'}
    |002| CONSTANT_Fieldref {Value='lsieun/sample/HelloWorld.t:Z', HexCode='090027004C'}
    |003| CONSTANT_Fieldref {Value='lsieun/sample/HelloWorld.c:C', HexCode='090027004D'}
    |004| CONSTANT_Fieldref {Value='lsieun/sample/HelloWorld.b:B', HexCode='090027004E'}
    |005| CONSTANT_Fieldref {Value='lsieun/sample/HelloWorld.s:S', HexCode='090027004F'}
    |006| CONSTANT_Fieldref {Value='lsieun/sample/HelloWorld.i:I', HexCode='0900270050'}
    |007| CONSTANT_Fieldref {Value='lsieun/sample/HelloWorld.l:J', HexCode='0900270051'}
    |008| CONSTANT_Float {Value='3.14', HexCode='044048F5C3'}
    |009| CONSTANT_Fieldref {Value='lsieun/sample/HelloWorld.f:F', HexCode='0900270052'}
    |010| CONSTANT_Double {Value='3.14159', HexCode='06400921F9F01B866E'}
    |012| CONSTANT_Fieldref {Value='lsieun/sample/HelloWorld.d:D', HexCode='0900270053'}
    |013| CONSTANT_Class {Value='java/lang/Object', HexCode='070054'}
    |014| CONSTANT_Fieldref {Value='lsieun/sample/HelloWorld.reference:Ljava/lang/Object;', HexCode='0900270055'}
    ......

code='2AB700012A04B500022A1078B500032A102FB500042A1100FFB500052A1103E7B500062A0AB500072A1208B500092A14000AB5000C2ABB000D59B70001B5000EB1'
    0: aload_0         // 2A
    1: invokespecial 1 // B70001
    4: aload_0         // 2A
    5: iconst_1        // 04
    6: putfield 2      // B50002
    9: aload_0         // 2A
   10: bipush 120      // 1078
   12: putfield 3      // B50003
   15: aload_0         // 2A
   16: bipush 47       // 102F
   18: putfield 4      // B50004
   21: aload_0         // 2A
   22: sipush 255      // 1100FF
   25: putfield 5      // B50005
   28: aload_0         // 2A
   29: sipush 999      // 1103E7
   32: putfield 6      // B50006
   35: aload_0         // 2A
   36: lconst_1        // 0A
   37: putfield 7      // B50007
   40: aload_0         // 2A
   41: ldc 8           // 1208
   43: putfield 9      // B50009
   46: aload_0         // 2A
   47: ldc2_w 10       // 14000A
   50: putfield 12     // B5000C
   53: aload_0         // 2A
   54: new 13          // BB000D
   57: dup             // 59
   58: invokespecial 1 // B70001
   61: putfield 14     // B5000E
   64: return          // B1


LocalVariableTable:
index  start_pc  length  name_and_type
    0         0      65  this:Llsieun/sample/HelloWorld;
```

This approach to initialization is simple and straightforward. It has the limitation that every object of type `HelloWorld` will get these same initialization values. Sometimes this is exactly what you need, but at other times you need more flexibility.

### 5.3. Constructor Initialization

The **constructor** can be used to perform **initialization**, and this gives you greater flexibility in your programming because you can call methods and perform actions at run time to determine the initial values. There’s one thing to keep in mind, however: You aren’t precluding the **automatic initialization**, which happens before the **constructor** is entered. So, for example, if you say:

```java
public class HelloWorld {
    int i;

    HelloWorld() {
        i = 7;
    }
}
```

then `i` will first be initialized to `0`, then to `7`. This is true with all the **primitive types** and with **object references**, including those that are given **explicit initialization** at the point of **definition**. For this reason, the compiler doesn’t try to force you to initialize elements in the constructor at any particular place, or before they are used — **initialization** is already guaranteed.




## 6. Extension: static data initialization

### 6.1. static Automation Initialization

学习目标：

示例代码：

```java
public class HelloWorld {
    public static int staticValue;

    public static void main(String[] args) {
        System.out.println("HelloWorld.staticValue = " + HelloWorld.staticValue);
    }
}
```

> 注意：这里没有生成`<clinit>:()V`方法

`main`方法输出结果：

```txt
HelloWorld.staticValue = 0
```

### 6.2. static Specifying Initialization

学习目标：

示例代码：

```java
public class HelloWorld {
    public static int staticValue = 1;
}
```

目标方法：`<clinit>:()V`

输出结果：

```txt
ConstantPool {
    |002| CONSTANT_Fieldref {Value='lsieun/sample/HelloWorld.staticValue:I', HexCode='0900030012'}
    ......

code='04B30002B1'
    0: iconst_1        // 04
    1: putstatic 2     // B30002
    4: return          // B1
```


### 6.3. Explicit static initialization

Java allows you to group **other static initializations** inside a special “**static clause**” (sometimes called a **static block**) in a class. It looks like this:

示例代码：

```java
public class HelloWorld {
    public static int staticValue;

    static {
        staticValue = 1;
    }
}
```

输出结果：

```txt
ConstantPool {
    |002| CONSTANT_Fieldref {Value='lsieun/sample/HelloWorld.staticValue:I', HexCode='0900030012'}
    ......

code='04B30002B1'
    0: iconst_1        // 04
    1: putstatic 2     // B30002
    4: return          // B1
```

It appears to be a method, but it’s just the `static` keyword followed by a block of code. This code, like other **static initializations**, is executed only once: **the first time you make an object of that class** or **the first time you access a static member of that class** (even if you never make an object of that class).

```java
public class HelloWorld {
    static String strA = "Hello";
    static String strB;

    static {
        strB = "World";
    }
}
```

目标方法：`<clinit>:()V`

输出结果：

```txt
ConstantPool {
    |002| CONSTANT_String {Value='Hello', HexCode='080016'}
    |003| CONSTANT_Fieldref {Value='lsieun/sample/HelloWorld.strA:Ljava/lang/String;', HexCode='0900060017'}
    |004| CONSTANT_String {Value='World', HexCode='080018'}
    |005| CONSTANT_Fieldref {Value='lsieun/sample/HelloWorld.strB:Ljava/lang/String;', HexCode='0900060019'}
    ......

code='1202B300031204B30005B1'
    0: ldc 2           // 1202
    2: putstatic 3     // B30003
    5: ldc 4           // 1204
    7: putstatic 5     // B30005
   10: return          // B1
```

## 7. Extension: static final data initialization

### 7.1. static final primitive data

学习目标：

示例代码：

```java
public class HelloWorld {
    //区别：这是用final修饰
    public static final int staticValue = 1;
}
```

注意：这里并没有生成`<clinit>:()V`方法

查看Field:`staticValue:I`

输出结果：

```txt
FieldInfo {Value='staticValue:I', AccessFlags='[ACC_PUBLIC,ACC_STATIC,ACC_FINAL]', Attrs='[ConstantValue]', HexCode='00190004000500010006000000020007'}

=================================================

ConstantValue {Value='1', HexCode='0006000000020007'}
```

示例代码：

```java
public class HelloWorld {
    public static final int staticValue;

    static {
        staticValue = 1;
    }
}
```

输出结果：

```txt
ConstantPool {
    |002| CONSTANT_Fieldref {Value='lsieun/sample/HelloWorld.staticValue:I', HexCode='0900030012'}
    ......

code='04B30002B1'
    0: iconst_1        // 04
    1: putstatic 2     // B30002
    4: return          // B1
```

### 7.2. static final Object Type


学习目标：

示例代码：

```java
public class HelloWorld {
    public static final Object obj = new Object();
}
```

输出结果：

```txt
ConstantPool {
    |001| CONSTANT_Methodref {Value='java/lang/Object.<init>:()V', HexCode='0A00020011'}
    |002| CONSTANT_Class {Value='java/lang/Object', HexCode='070012'}
    |003| CONSTANT_Fieldref {Value='lsieun/sample/HelloWorld.obj:Ljava/lang/Object;', HexCode='0900040013'}
    ......

code='BB000259B70001B30003B1'
    0: new 2           // BB0002
    3: dup             // 59
    4: invokespecial 1 // B70001
    7: putstatic 3     // B30003
   10: return          // B1
```

## 8. Extension: Order of Initialization

To summarize the process of creating **an object**, consider a class called `Dog`:

- (1) Even though it doesn’t explicitly use the `static` keyword, the **constructor** is actually a `static` method. So the first time an object of type `Dog` is created, or the first time a **static method** or **static field** of class Dog is accessed, the Java interpreter must locate `Dog.class`, which it does by searching through the **classpath**.

- (2) As `Dog.class` is loaded (creating a `Class` object), all of its **static initializers** are run. Thus, **static initialization** takes place only once, as the **Class object** is loaded for the first time.

- (3) When you create a `new Dog()`, the **construction process** for a `Dog` object first **allocates enough storage** for a `Dog` object on the **heap**.

- (4) This **storage** is wiped to **zero**, automatically setting all the **primitives** in that `Dog` object to their **default values** (**zero** for numbers and the equivalent for `boolean` and `char`) and the **references** to `null`.

- (5) Any **initializations** that occur at the point of **field definition** are executed.

- (6) **Constructors** are executed. This might actually involve a fair amount of activity, especially when inheritance is involved.

Within a class, **the order of initialization** is determined by **the order that the variables are defined within the class**. The variable definitions may be scattered throughout and in between method definitions, but the **variables** are initialized before any methods can be called — even the constructor.


