# Opcode Objects

<!-- TOC -->

- [1. Outter: new dup invokespecial](#1-outter-new-dup-invokespecial)
  - [1.1. new Object](#11-new-object)
  - [1.2. new HelloWorld](#12-new-helloworld)
- [2. Inner: Constructor](#2-inner-constructor)
  - [2.1. HelloWorld extends Object](#21-helloworld-extends-object)
  - [2.2. HelloWorld extends ParentClass](#22-helloworld-extends-parentclass)
  - [2.3. Object Constructor](#23-object-constructor)
- [3. Inner: Static initializer](#3-inner-static-initializer)
- [4. Summing-up](#4-summing-up)

<!-- /TOC -->

**Objects**. These instructions are used to create objects, lock them, test their type, etc. For instance the `NEW type` instruction pushes a new object of type `type` on the stack (where `type` is an internal name).

## 1. Outter: new dup invokespecial

### 1.1. new Object

学习目标：

- `new`
- `dup`
- `invokespecial`
- `pop`

示例代码：

```java
public class HelloWorld {
    public void testSimple() {
        new Object();
    }
}
```

输出结果：

```txt
ConstantPool {
    |001| CONSTANT_Methodref {Value='java/lang/Object.<init>:()V', HexCode='0A0002000E'}
    |002| CONSTANT_Class {Value='java/lang/Object', HexCode='07000F'}
    ......

code='BB000259B7000157B1'
    0: new 2           // BB0002
    3: dup             // 59
    4: invokespecial 1 // B70001
    7: pop             // 57
    8: return          // B1


LocalVariableTable:
index  start_pc  length  name_and_type
    0         0       9  this:Llsieun/sample/HelloWorld;
```

### 1.2. new HelloWorld

学习目标：

- `new/dup/invokespecial`：见到这三个opcode，就表示创建对象。

示例代码：

```java
public class HelloWorld {
    public void testSimple() {
        new HelloWorld();
    }
}
```

输出结果：

```txt
ConstantPool {
    |001| CONSTANT_Methodref {Value='java/lang/Object.<init>:()V', HexCode='0A0004000F'}
    |002| CONSTANT_Class {Value='lsieun/sample/HelloWorld', HexCode='070010'}
    |003| CONSTANT_Methodref {Value='lsieun/sample/HelloWorld.<init>:()V', HexCode='0A0002000F'}
    ......

code='BB000259B7000357B1'
    0: new 2           // BB0002
    3: dup             // 59
    4: invokespecial 3 // B70003
    7: pop             // 57
    8: return          // B1


LocalVariableTable:
index  start_pc  length  name_and_type
    0         0       9  this:Llsieun/sample/HelloWorld;
```

## 2. Inner: Constructor

### 2.1. HelloWorld extends Object

学习目标：

**Default constructors**. A default constructor (a.k.a. a “no-arg” constructor) is one without arguments that is used to create a “default object.” If you create a class that has no constructors, the compiler will automatically create a default constructor for you. Without it, you would have no method to call to build the object. However, if you define any constructors (with or without arguments), the compiler will not synthesize(合成) one for you.

When you don’t put in any constructors, it’s as if the compiler says, “You are bound to need some constructor, so let me make one for you.” But if you write a constructor, the compiler says, “You’ve written a constructor so you know what you’re doing; if you didn’t put in a default it’s because you meant to leave it out.”

示例代码：

```java
public class HelloWorld {
    //
}
```

or

```java
public class HelloWorld {
    public HelloWorld() {
        super();
    }
}
```

目标方法：`<init>:()V`

输出结果：

```txt
ConstantPool {
    |001| CONSTANT_Methodref {Value='java/lang/Object.<init>:()V', HexCode='0A0003000D'}
    ......

code='2AB70001B1'
    0: aload_0         // 2A
    1: invokespecial 1 // B70001
    4: return          // B1


LocalVariableTable:
index  start_pc  length  name_and_type
    0         0       5  this:Llsieun/sample/HelloWorld;
```

### 2.2. HelloWorld extends ParentClass

学习目标：

示例代码：

```java
public class ParentClass {
}

public class HelloWorld extends ParentClass {
    //
}
```

输出结果：

```txt
ConstantPool {
    |001| CONSTANT_Methodref {Value='lsieun/sample/ParentClass.<init>:()V', HexCode='0A0003000D'}
    |002| CONSTANT_Class {Value='lsieun/sample/HelloWorld', HexCode='07000E'}
    |003| CONSTANT_Class {Value='lsieun/sample/ParentClass', HexCode='07000F'}
    ......

code='2AB70001B1'
    0: aload_0         // 2A
    1: invokespecial 1 // B70001
    4: return          // B1


LocalVariableTable:
index  start_pc  length  name_and_type
    0         0       5  this:Llsieun/sample/HelloWorld;
```

### 2.3. Object Constructor

学习目标：

除了`java.lang.Object`类，其他所有类都有父类，都涉及到在`<init>:()V`方法中调用`super()`方法。那么，在`java.lang.Object`类的`<init>:()V`方法中，是什么情况呢？

示例代码：

```java
// NO NEED CODE
```

输出结果：

```txt
code='B1'
    0: return          // B1
```

## 3. Inner: Static initializer

学习目标：

示例代码：

```java
public class HelloWorld {
    public static int intValue = 64;
}
```

目标方法：`<clinit>:()V`

输出结果：

```txt
ConstantPool {
    |002| CONSTANT_Fieldref {Value='lsieun/sample/HelloWorld.intValue:I', HexCode='0900030012'}
    ......

code='1040B30002B1'
    0: bipush 64       // 1040
    2: putstatic 2     // B30002
    5: return          // B1
```

## 4. Summing-up

知识总结

| opcode | mnemonic symbol | meaning                               |
| ------ | --------------- | ------------------------------------- |
| `87`   | `pop`           | Pop the top operand stack value       |
| `89`   | `dup`           | Duplicate the top operand stack value |
| `183`  | `invokespecial` |                                       |
| `187`  | `new`           | Create new object                     |

