# Opcode Fields

<!-- TOC -->

- [1. ClassFile fields](#1-classfile-fields)
- [2. non-static field](#2-non-static-field)
  - [2.1. getfield](#21-getfield)
  - [2.2. putfield](#22-putfield)
- [3. static field](#3-static-field)
  - [3.1. getstatic](#31-getstatic)
  - [3.2. putstatic](#32-putstatic)
- [4. Summing-up](#4-summing-up)

<!-- /TOC -->

**Fields**. These instructions read or write the value of a field. `GETFIELD owner name desc` pops an object reference, and pushes the value of its `name` field. `PUTFIELD owner name desc` pops a value and an object reference, and stores this value in its `name` field. In both cases the object must be of type `owner`, and its field must be of type `desc`. `GETSTATIC` and `PUTSTATIC` are similar instructions, but for `static` fields.

注意：这里讲Fields，重点并不是讲“如何定义Fields”，而是讲“如何使用Fields”。“如何定义Fields”是属于`ClassFile`结构的内容，而“如何使用Fields”是属于`opcode`的内容。

## 1. ClassFile fields

```txt
ClassFile {
    u4 magic_number;
    u2 minor_version;
    u2 major_version;
    u2 constant_pool_count;
    cp_info constant_pool[constant_pool_count-1];
    u2 access_flags;
    u2 this_class;
    u2 super_class;
    u2 interfaces_count;
    u2 interfaces[interfaces_count];
    u2 fields_count;
    field_info fields[fields_count];
    u2 methods_count;
    method_info methods[methods_count];
    u2 attributes_count;
    attribute_info attributes[attributes_count];
}
```

## 2. non-static field

### 2.1. getfield

学习目标：

示例代码：

```java
public class HelloWorld {
    public int value;

    public void testSimple() {
        int i = this.value;
    }
}
```

输出结果：

```txt
ConstantPool {
    |001| CONSTANT_Methodref {Value='java/lang/Object.<init>:()V', HexCode='0A00040012'}
    |002| CONSTANT_Fieldref {Value='lsieun/sample/HelloWorld.value:I', HexCode='0900030013'}
    ......

code='2AB400023CB1'
    0: aload_0         // 2A
    1: getfield 2      // B40002
    4: istore_1        // 3C
    5: return          // B1


LocalVariableTable:
index  start_pc  length  name_and_type
    0         0       6  this:Llsieun/sample/HelloWorld;
    1         5       1  i:I
```

### 2.2. putfield

学习目标：

示例代码：

```java
public class HelloWorld {
    public int value;

    public void testSimple() {
        this.value = 0;
    }
}
```

输出结果：

```txt
ConstantPool {
    |002| CONSTANT_Fieldref {Value='lsieun/sample/HelloWorld.value:I', HexCode='0900030012'}
    ......

code='2A03B50002B1'
    0: aload_0         // 2A
    1: iconst_0        // 03
    2: putfield 2      // B50002
    5: return          // B1


LocalVariableTable:
index  start_pc  length  name_and_type
    0         0       6  this:Llsieun/sample/HelloWorld;
```

## 3. static field

### 3.1. getstatic

学习目标：

示例代码：

```java
public class HelloWorld {
    public static int staticValue;

    public void testSimple() {
        int i = HelloWorld.staticValue;
    }
}
```

输出结果：

```txt
ConstantPool {
    |001| CONSTANT_Methodref {Value='java/lang/Object.<init>:()V', HexCode='0A00040012'}
    |002| CONSTANT_Fieldref {Value='lsieun/sample/HelloWorld.staticValue:I', HexCode='0900030013'}
    ......

code='B200023CB1'
    0: getstatic 2     // B20002
    3: istore_1        // 3C
    4: return          // B1


LocalVariableTable:
index  start_pc  length  name_and_type
    0         0       5  this:Llsieun/sample/HelloWorld;
    1         4       1  i:I
```

### 3.2. putstatic

学习目标：

示例代码：

```java
public class HelloWorld {
    public static int staticValue;

    public void testSimple() {
        HelloWorld.staticValue = 1;
    }
}
```

输出结果：

```txt
ConstantPool {
    |002| CONSTANT_Fieldref {Value='lsieun/sample/HelloWorld.staticValue:I', HexCode='0900030012'}
    ......

code='04B30002B1'
    0: iconst_1        // 04
    1: putstatic 2     // B30002
    4: return          // B1


LocalVariableTable:
index  start_pc  length  name_and_type
    0         0       5  this:Llsieun/sample/HelloWorld;
```

## 4. Summing-up

知识总结
