# Class Member

<!-- TOC -->

- [1. constructor invocation](#1-constructor-invocation)
- [2. non-static method invocation](#2-non-static-method-invocation)
  - [2.1. public method](#21-public-method)
  - [2.2. protected method](#22-protected-method)
  - [2.3. private method](#23-private-method)
  - [2.4. package method](#24-package-method)
  - [2.5. use `this` only when necessary](#25-use-this-only-when-necessary)
- [3. static method invocation](#3-static-method-invocation)
  - [3.1. static public method](#31-static-public-method)
  - [3.2. static protected method](#32-static-protected-method)
  - [3.3. static priavte method](#33-static-priavte-method)
  - [3.4. static package method](#34-static-package-method)
- [4. Interface Method](#4-interface-method)
  - [4.1. interface non-static method](#41-interface-non-static-method)
  - [4.2. interface default method](#42-interface-default-method)
  - [4.3. interface static method](#43-interface-static-method)
- [5. Other Method](#5-other-method)
  - [5.1. parent method](#51-parent-method)
- [6. Summing-up](#6-summing-up)

<!-- /TOC -->

可以写出来的方法有许多种，我们

constructor
public/protected/private
static public/protected/private

InterfaceMethod
parentMethod

## 1. constructor invocation

学习目标：

示例代码：

```java
public class HelloWorld {
    public void testSimple() {
        HelloWorld instance = new HelloWorld();
    }
}
```

输出结果：

```txt
ConstantPool {
    |001| CONSTANT_Methodref {Value='java/lang/Object.<init>:()V', HexCode='0A00040010'}
    |002| CONSTANT_Class {Value='lsieun/sample/HelloWorld', HexCode='070011'}
    |003| CONSTANT_Methodref {Value='lsieun/sample/HelloWorld.<init>:()V', HexCode='0A00020010'}

code='BB000259B700034CB1'
    0: new 2           // BB0002
    3: dup             // 59
    4: invokespecial 3 // B70003
    7: astore_1        // 4C
    8: return          // B1


LocalVariableTable:
index  start_pc  length  name_and_type
    0         0       9  this:Llsieun/sample/HelloWorld;
    1         8       1  instance:Llsieun/sample/HelloWorld;
```

## 2. non-static method invocation

### 2.1. public method

学习目标：

- `invokevirtual`

示例代码：

```java
public class HelloWorld {
    public void targetMethod() {
        //
    }

    public void testSimple() {
        targetMethod();
    }
}
```

输出结果：

```txt
ConstantPool {
    |002| CONSTANT_Methodref {Value='lsieun/sample/HelloWorld.targetMethod:()V', HexCode='0A00030011'}
    ......

code='2AB60002B1'
    0: aload_0         // 2A
    1: invokevirtual 2 // B60002
    4: return          // B1


LocalVariableTable:
index  start_pc  length  name_and_type
    0         0       5  this:Llsieun/sample/HelloWorld;
```

### 2.2. protected method

学习目标：

示例代码：

```java
public class HelloWorld {
    protected void targetMethod() {
        //
    }

    public void testSimple() {
        targetMethod();
    }
}
```

输出结果：

```txt
ConstantPool {
    |002| CONSTANT_Methodref {Value='lsieun/sample/HelloWorld.targetMethod:()V', HexCode='0A00030011'}
    ......

code='2AB60002B1'
    0: aload_0         // 2A
    1: invokevirtual 2 // B60002
    4: return          // B1


LocalVariableTable:
index  start_pc  length  name_and_type
    0         0       5  this:Llsieun/sample/HelloWorld;
```

### 2.3. private method

学习目标：

- `invokespecial`

示例代码：

```java
public class HelloWorld {
    private void targetMethod() {
        //
    }

    public void testSimple() {
        targetMethod();
    }
}
```

输出结果：

```txt
ConstantPool {
    |002| CONSTANT_Methodref {Value='lsieun/sample/HelloWorld.targetMethod:()V', HexCode='0A00030011'}
    ......

code='2AB70002B1'
    0: aload_0         // 2A
    1: invokespecial 2 // B70002
    4: return          // B1


LocalVariableTable:
index  start_pc  length  name_and_type
    0         0       5  this:Llsieun/sample/HelloWorld;
```

### 2.4. package method

学习目标：

示例代码：

```java
public class HelloWorld {
    void targetMethod() {
        //
    }

    public void testSimple() {
        targetMethod();
    }
}
```

输出结果：

```txt
ConstantPool {
    |002| CONSTANT_Methodref {Value='lsieun/sample/HelloWorld.targetMethod:()V', HexCode='0A00030011'}
    ......

code='2AB60002B1'
    0: aload_0         // 2A
    1: invokevirtual 2 // B60002
    4: return          // B1


LocalVariableTable:
index  start_pc  length  name_and_type
    0         0       5  this:Llsieun/sample/HelloWorld;
```

### 2.5. use `this` only when necessary

To allow you to write the code in a convenient **object-oriented syntax** in which you “send a message to an object,” the compiler does some undercover work for you. There’s a secret first argument passed to the method `peel()`, and that argument is the reference to the object that’s being manipulated. So the two method calls become something like:

```java
Banana.peel(a, 1);
Banana.peel(b, 2);
```

Suppose you’re inside a method and you’d like to get the reference to the **current object**. Since that **reference** is passed secretly by the compiler, there’s no identifier for it. However, for this purpose there’s a keyword: `this`. The `this` keyword — which can be used only inside a non-static method — produces the reference to the object that the method has been called for. You can treat **the reference** just like any other object reference. Keep in mind that if you’re calling a method of your class from within another method of your class, you don’t need to use `this`. You simply call the method. The current `this` reference is automatically used for the other method. Thus you can say:

```java
//: initialization/Apricot.java
public class Apricot {
    void pick() { /* ... */ }
    void pit() { pick(); /* ... */ }
} ///:~
```

Some people will obsessively(着迷一般地) put `this` in front of every **method call** and **field** reference, arguing that it makes it “clearer and more explicit.” **Don’t do it**. There’s a reason that we use high-level languages: They do things for us. If you put `this` in when it’s not necessary, you will confuse and annoy everyone who reads your code, since all the rest of the code they’ve read won’t use `this` everywhere. People expect `this` to be used only when it is necessary. Following a consistent and straightforward coding style saves time and money. -- 《Think in Java》

## 3. static method invocation

### 3.1. static public method

学习目标：

- `invokestatic`: Invoke a class (`static`) method

示例代码：

```java
public class HelloWorld {
    public static void targetMethod() {
        //
    }

    public void testSimple() {
        targetMethod();
    }
}
```

输出结果：

```txt
ConstantPool {
    |002| CONSTANT_Methodref {Value='lsieun/sample/HelloWorld.targetMethod:()V', HexCode='0A00030011'}
    ......

code='B80002B1'
    0: invokestatic 2  // B80002
    3: return          // B1


LocalVariableTable:
index  start_pc  length  name_and_type
    0         0       4  this:Llsieun/sample/HelloWorld;
```

### 3.2. static protected method

学习目标：

示例代码：

```java
public class HelloWorld {
    protected static void targetMethod() {
        //
    }

    public void testSimple() {
        targetMethod();
    }
}
```

输出结果：

```txt
ConstantPool {
    |002| CONSTANT_Methodref {Value='lsieun/sample/HelloWorld.targetMethod:()V', HexCode='0A00030011'}
    ......

code='B80002B1'
    0: invokestatic 2  // B80002
    3: return          // B1


LocalVariableTable:
index  start_pc  length  name_and_type
    0         0       4  this:Llsieun/sample/HelloWorld;
```

### 3.3. static priavte method

学习目标：

示例代码：

```java
public class HelloWorld {
    private static void targetMethod() {
        //
    }

    public void testSimple() {
        targetMethod();
    }
}
```

输出结果：

```txt
ConstantPool {
    |002| CONSTANT_Methodref {Value='lsieun/sample/HelloWorld.targetMethod:()V', HexCode='0A00030011'}
    ......

code='B80002B1'
    0: invokestatic 2  // B80002
    3: return          // B1


LocalVariableTable:
index  start_pc  length  name_and_type
    0         0       4  this:Llsieun/sample/HelloWorld;
```

### 3.4. static package method

学习目标：

示例代码：

```java
public class HelloWorld {
    static void targetMethod() {
        //
    }

    public void testSimple() {
        targetMethod();
    }
}
```

输出结果：

```txt
ConstantPool {
    |002| CONSTANT_Methodref {Value='lsieun/sample/HelloWorld.targetMethod:()V', HexCode='0A00030011'}
    ......

code='B80002B1'
    0: invokestatic 2  // B80002
    3: return          // B1


LocalVariableTable:
index  start_pc  length  name_and_type
    0         0       4  this:Llsieun/sample/HelloWorld;
```

## 4. Interface Method

### 4.1. interface non-static method

学习目标：

- `invokeinterface`: Invoke interface method

示例代码：

```java
public class HelloWorld {
    public void testSimple() {
        MyInterface instance = null;
        instance.targetMethod();
    }
}

interface MyInterface {
    void targetMethod();
}
```

输出结果：

```txt
ConstantPool {
    |002| CONSTANT_InterfaceMethodref {Value='lsieun/sample/MyInterface.targetMethod:()V', HexCode='0B00120013'}
    ......

code='014C2BB900020100B1'
    0: aconst_null     // 01
    1: astore_1        // 4C
    2: aload_1         // 2B
    3: invokeinterface 2 1 0// B900020100
    8: return          // B1


LocalVariableTable:
index  start_pc  length  name_and_type
    0         0       9  this:Llsieun/sample/HelloWorld;
    1         2       7  instance:Llsieun/sample/MyInterface;
```

### 4.2. interface default method

学习目标：

示例代码：

```java
public class HelloWorld {
    public void testSimple() {
        MyInterface instance = null;
        instance.targetMethod();
    }
}

interface MyInterface {
    default void targetMethod() {
        //
    }
}
```

输出结果：

```txt
ConstantPool {
    |002| CONSTANT_InterfaceMethodref {Value='lsieun/sample/MyInterface.targetMethod:()V', HexCode='0B00120013'}
    ......

code='014C2BB900020100B1'
    0: aconst_null     // 01
    1: astore_1        // 4C
    2: aload_1         // 2B
    3: invokeinterface 2 1 0// B900020100
    8: return          // B1


LocalVariableTable:
index  start_pc  length  name_and_type
    0         0       9  this:Llsieun/sample/HelloWorld;
    1         2       7  instance:Llsieun/sample/MyInterface;
```

### 4.3. interface static method

学习目标：

示例代码：

```java
public class HelloWorld {
    public void testSimple() {
        MyInterface.targetMethod();
    }
}

interface MyInterface {
    static void targetMethod() {
        //
    }
}
```

输出结果：

```txt
ConstantPool {
    |002| CONSTANT_InterfaceMethodref {Value='lsieun/sample/MyInterface.targetMethod:()V', HexCode='0B00100011'}
    ......

code='B80002B1'
    0: invokestatic 2  // B80002
    3: return          // B1


LocalVariableTable:
index  start_pc  length  name_and_type
    0         0       4  this:Llsieun/sample/HelloWorld;
```

## 5. Other Method

### 5.1. parent method

学习目标：

- `invokevirtual`: Invoke instance method; dispatch based on class

示例代码：

```java
public class HelloWorld {
    public void testSimple() {
        String str = this.toString();
    }
}
```

输出结果：

```txt
ConstantPool {
    |002| CONSTANT_Methodref {Value='java/lang/Object.toString:()Ljava/lang/String;', HexCode='0A00040012'}
    ......

code='2AB600024CB1'
    0: aload_0         // 2A
    1: invokevirtual 2 // B60002
    4: astore_1        // 4C
    5: return          // B1


LocalVariableTable:
index  start_pc  length  name_and_type
    0         0       6  this:Llsieun/sample/HelloWorld;
    1         5       1  str:Ljava/lang/String;
```

## 6. Summing-up

知识整理

| opcode | mnemonic symbol   | meaning                                         |
| ------ | ----------------- | ----------------------------------------------- |
| `182`  | `invokevirtual`   | Invoke instance method; dispatch based on class |
| `183`  | `invokespecial`   |                                                 |
| `184`  | `invokestatic`    | Invoke a class (static) method                  |
| `185`  | `invokeinterface` | Invoke interface method                         |
| `186`  | `invokedynamic`   | Invoke a dynamically-computed call site         |

