# Class Member

<!-- TOC -->

- [1. 特殊方法：构造函数](#1-%E7%89%B9%E6%AE%8A%E6%96%B9%E6%B3%95%E6%9E%84%E9%80%A0%E5%87%BD%E6%95%B0)
  - [1.1. 空空的构造器](#11-%E7%A9%BA%E7%A9%BA%E7%9A%84%E6%9E%84%E9%80%A0%E5%99%A8)
  - [1.2. 有一个字段](#12-%E6%9C%89%E4%B8%80%E4%B8%AA%E5%AD%97%E6%AE%B5)
- [2. 特殊方法：类初始化函数](#2-%E7%89%B9%E6%AE%8A%E6%96%B9%E6%B3%95%E7%B1%BB%E5%88%9D%E5%A7%8B%E5%8C%96%E5%87%BD%E6%95%B0)
  - [2.1. static int](#21-static-int)
  - [2.2. static final int](#22-static-final-int)
  - [2.3. static Integer](#23-static-integer)
  - [2.4. static Object instance](#24-static-object-instance)
- [3. 静态字段](#3-%E9%9D%99%E6%80%81%E5%AD%97%E6%AE%B5)
  - [3.1. 获取静态字段](#31-%E8%8E%B7%E5%8F%96%E9%9D%99%E6%80%81%E5%AD%97%E6%AE%B5)
  - [3.2. 设置静态字段](#32-%E8%AE%BE%E7%BD%AE%E9%9D%99%E6%80%81%E5%AD%97%E6%AE%B5)
- [4. 非静态字段](#4-%E9%9D%9E%E9%9D%99%E6%80%81%E5%AD%97%E6%AE%B5)
  - [4.1. 获取非静态字段](#41-%E8%8E%B7%E5%8F%96%E9%9D%9E%E9%9D%99%E6%80%81%E5%AD%97%E6%AE%B5)
  - [4.2. 设置非静态字段](#42-%E8%AE%BE%E7%BD%AE%E9%9D%9E%E9%9D%99%E6%80%81%E5%AD%97%E6%AE%B5)
- [方法调用](#%E6%96%B9%E6%B3%95%E8%B0%83%E7%94%A8)
  - [静态方法调用](#%E9%9D%99%E6%80%81%E6%96%B9%E6%B3%95%E8%B0%83%E7%94%A8)
- [非静态方法调用](#%E9%9D%9E%E9%9D%99%E6%80%81%E6%96%B9%E6%B3%95%E8%B0%83%E7%94%A8)
  - [接口方法调用](#%E6%8E%A5%E5%8F%A3%E6%96%B9%E6%B3%95%E8%B0%83%E7%94%A8)

<!-- /TOC -->

可以写出来的方法有许多种，我们

## 1. 特殊方法：构造函数

### 1.1. 空空的构造器

示例代码：

```java
public class HelloWorld {

}
```

或

```java
public class HelloWorld {
    public HelloWorld() {
        super();
    }
}
```

输出结果：

```txt
ConstantPool {
    |001| CONSTANT_Methodref {Value='java/lang/Object.<init>:()V', HexCode='0A0003000D'}
    ......

code='2AB70001B1'
    0: aload_0         // 2A
    1: invokespecial 1 // B70001
    4: return          // B1


LocalVariableTable:
index  start_pc  length  name_and_type
    0         0       5  this:Llsieun/sample/HelloWorld;
```



### 1.2. 有一个字段

目标方法：`<init>:()V`

示例代码：

```java
public class HelloWorld {
    private int intValue = 3;
}
```

或

```java
public class HelloWorld {
    private int intValue;

    public HelloWorld() {
        this.intValue = 3;
    }
}
```

输出结果：

```txt
ConstantPool {
    |001| CONSTANT_Methodref {Value='java/lang/Object.<init>:()V', HexCode='0A00040010'}
    |002| CONSTANT_Fieldref {Value='lsieun/sample/HelloWorld.intValue:I', HexCode='0900030011'}
    ......

code='2AB700012A06B50002B1'
    0: aload_0         // 2A
    1: invokespecial 1 // B70001
    4: aload_0         // 2A
    5: iconst_3        // 06
    6: putfield 2      // B50002
    9: return          // B1


LocalVariableTable:
index  start_pc  length  name_and_type
    0         0      10  this:Llsieun/sample/HelloWorld;
......
```



## 2. 特殊方法：类初始化函数

目标方法：`<clinit>:()V`

### 2.1. static int

学习目标：

- `putstatic indexbyte1 indexbyte2`: Set static field in class

示例代码：

```java
public class HelloWorld {
    public static int intValue = 1;
}
```

输出结果：

```txt
ConstantPool {
    |002| CONSTANT_Fieldref {Value='lsieun/sample/HelloWorld.intValue:I', HexCode='0900030012'}

code='04B30002B1'
    0: iconst_1        // 04
    1: putstatic 2     // B30002
    4: return          // B1
```

### 2.2. static final int

学习目标：

- `static final int`定义的变量是在ConstantValue中的。

示例代码：

```java
public class HelloWorld {
    public static final int intValue = 1;
}
```

注意：此时并不存在`<clinit>:()V`方法。

输出结果：

```txt
FieldInfo {Value='intValue:I', AccessFlags='[ACC_PUBLIC,ACC_STATIC,ACC_FINAL]', Attrs='[ConstantValue]', HexCode='00190004000500010006000000020007'}

=================================================

ConstantValue {Value='1', HexCode='0006000000020007'}
```

### 2.3. static Integer

学习目标：

- 对比“static int”和“static Integer”对于`final`的区别

示例代码：

```java
public class HelloWorld {
    // 关注点： 这里没有使用final关键字
    public static Integer intValue = 1;
}
```

和

```java
public class HelloWorld {
    // 关注点： 这里使用了final关键字
    public static final Integer intValue = 1;
}
```

两段代码具有相同的输出结果。

输出结果：

```txt
ConstantPool {
    |002| CONSTANT_Methodref {Value='java/lang/Integer.valueOf:(I)Ljava/lang/Integer;', HexCode='0A00130014'}
    |003| CONSTANT_Fieldref {Value='lsieun/sample/HelloWorld.intValue:Ljava/lang/Integer;', HexCode='0900040015'}
    ......

code='04B80002B30003B1'
    0: iconst_1        // 04
    1: invokestatic 2  // B80002
    4: putstatic 3     // B30003
    7: return          // B1
```

### 2.4. static Object instance

学习目标：

- 观察，处理`static Integer`和`static Object`的opcode是相同的。

示例代码：

```java
public class HelloWorld {
    public static Object instance = new Object();
}
```

输出结果：

```txt
ConstantPool {
    |001| CONSTANT_Methodref {Value='java/lang/Object.<init>:()V', HexCode='0A00020011'}
    |002| CONSTANT_Class {Value='java/lang/Object', HexCode='070012'}
    |003| CONSTANT_Fieldref {Value='lsieun/sample/HelloWorld.instance:Ljava/lang/Object;', HexCode='0900040013'}
    ......

code='BB000259B70001B30003B1'
    0: new 2           // BB0002
    3: dup             // 59
    4: invokespecial 1 // B70001
    7: putstatic 3     // B30003
   10: return          // B1
```

## 3. 静态字段

### 3.1. 获取静态字段

学习目标：

- `getstatic`: Get `static` field from class

示例代码：

```java
public class HelloWorld {
    public static int intValue = 5;

    public void testSimple() {
        int i = HelloWorld.intValue;
    }
}
```

输出结果：

```txt
ConstantPool {
    |002| CONSTANT_Fieldref {Value='lsieun/sample/HelloWorld.intValue:I', HexCode='0900030014'}
    ......

code='B200023CB1'
    0: getstatic 2     // B20002
    3: istore_1        // 3C
    4: return          // B1


LocalVariableTable:
index  start_pc  length  name_and_type
    0         0       5  this:Llsieun/sample/HelloWorld;
    1         4       1  i:I
```

### 3.2. 设置静态字段

学习目标：

- `putstatic`: Set `static` field in class

示例代码：

```java
public class HelloWorld {
    public static int intValue = 5;

    public void testSimple() {
        HelloWorld.intValue = 3;
    }
}
```

输出结果：

```txt
ConstantPool {
    |002| CONSTANT_Fieldref {Value='lsieun/sample/HelloWorld.intValue:I', HexCode='0900030013'}
    ......

code='06B30002B1'
    0: iconst_3        // 06
    1: putstatic 2     // B30002
    4: return          // B1


LocalVariableTable:
index  start_pc  length  name_and_type
    0         0       5  this:Llsieun/sample/HelloWorld;
```

## 4. 非静态字段

### 4.1. 获取非静态字段

学习目标：

- `getfield`: Fetch field from object

示例代码：

```java
public class HelloWorld {
    public int intValue;

    public void testSimple() {
        int i = this.intValue;
    }
}
```

输出结果：

```txt
ConstantPool {
    |002| CONSTANT_Fieldref {Value='lsieun/sample/HelloWorld.intValue:I', HexCode='0900030013'}
    ......

code='2AB400023CB1'
    0: aload_0         // 2A
    1: getfield 2      // B40002
    4: istore_1        // 3C
    5: return          // B1


LocalVariableTable:
index  start_pc  length  name_and_type
    0         0       6  this:Llsieun/sample/HelloWorld;
    1         5       1  i:I
```

### 4.2. 设置非静态字段

学习目标：

- `putfield`: Set field in object

示例代码：

```java
public class HelloWorld {
    public int intValue;

    public void testSimple() {
        this.intValue = 3;
    }
}
```

输出结果：

```txt
ConstantPool {
    |002| CONSTANT_Fieldref {Value='lsieun/sample/HelloWorld.intValue:I', HexCode='0900030012'}

code='2A06B50002B1'
    0: aload_0         // 2A
    1: iconst_3        // 06
    2: putfield 2      // B50002
    5: return          // B1


LocalVariableTable:
index  start_pc  length  name_and_type
    0         0       6  this:Llsieun/sample/HelloWorld;
```

## 方法调用

### 静态方法调用

学习目标：

- `invokestatic`: Invoke a class (`static`) method

示例代码：

```java
public class HelloWorld {
    public void testSimple() {
        int i = Math.abs(-1);
    }
}
```

输出结果：

```txt
ConstantPool {
    |002| CONSTANT_Methodref {Value='java/lang/Math.abs:(I)I', HexCode='0A00120013'}
    ......

code='02B800023CB1'
    0: iconst_m1       // 02
    1: invokestatic 2  // B80002
    4: istore_1        // 3C
    5: return          // B1


LocalVariableTable:
index  start_pc  length  name_and_type
    0         0       6  this:Llsieun/sample/HelloWorld;
    1         5       1  i:I
```

## 非静态方法调用

学习目标：

- `invokevirtual`: Invoke instance method; dispatch based on class

示例代码：

```java
public class HelloWorld {
    public void testSimple() {
        String str = this.toString();
    }
}
```

输出结果：

```txt
ConstantPool {
    |002| CONSTANT_Methodref {Value='java/lang/Object.toString:()Ljava/lang/String;', HexCode='0A00040012'}
    ......

code='2AB600024CB1'
    0: aload_0         // 2A
    1: invokevirtual 2 // B60002
    4: astore_1        // 4C
    5: return          // B1


LocalVariableTable:
index  start_pc  length  name_and_type
    0         0       6  this:Llsieun/sample/HelloWorld;
    1         5       1  str:Ljava/lang/String;
```

### 接口方法调用

学习目标：

- `invokeinterface`: Invoke interface method

示例代码：

```java
public class HelloWorld {
    public void testSimple() {
        Runnable instance = null;
        instance.run();
    }
}
```

输出结果：

```txt
ConstantPool {
    |002| CONSTANT_InterfaceMethodref {Value='java/lang/Runnable.run:()V', HexCode='0B00120013'}
    ......

code='014C2BB900020100B1'
    0: aconst_null     // 01
    1: astore_1        // 4C
    2: aload_1         // 2B
    3: invokeinterface 2 1 0// B900020100
    8: return          // B1


LocalVariableTable:
index  start_pc  length  name_and_type
    0         0       9  this:Llsieun/sample/HelloWorld;
    1         2       7  instance:Ljava/lang/Runnable;
```

