## 007

## 9. Boxing Conversion

### 9.1. boolean to Boolean

```java
public class HelloWorld {
    public void testSimple() {
        Boolean bool_true = true;
        Boolean bool_false = false;
    }
}
```

```txt
ConstantPool {
    |002| CONSTANT_Methodref {Value='java/lang/Boolean.valueOf:(Z)Ljava/lang/Boolean;', HexCode='0A00130014'}
    ......

code='04B800024C03B800024DB1'
    0: iconst_1        // 04
    1: invokestatic 2  // B80002
    4: astore_1        // 4C
    5: iconst_0        // 03
    6: invokestatic 2  // B80002
    9: astore_2        // 4D
   10: return          // B1


LocalVariableTable:
index  start_pc  length  name_and_type
    0         0      11  this:Llsieun/sample/HelloWorld;
    1         5       6  bool_true:Ljava/lang/Boolean;
    2        10       1  bool_false:Ljava/lang/Boolean;
```

### 9.2. byte to Byte

```java
public class HelloWorld {
    public void testSimple() {
        Byte b_1 = 1;
    }
}
```

```txt
ConstantPool {
    |002| CONSTANT_Methodref {Value='java/lang/Byte.valueOf:(B)Ljava/lang/Byte;', HexCode='0A00120013'}
    ......

code='04B800024CB1'
    0: iconst_1        // 04
    1: invokestatic 2  // B80002
    4: astore_1        // 4C
    5: return          // B1


LocalVariableTable:
index  start_pc  length  name_and_type
    0         0       6  this:Llsieun/sample/HelloWorld;
    1         5       1  b_1:Ljava/lang/Byte;
```

### 9.3. short to Short

```java
public class HelloWorld {
    public void testSimple() {
        Short short_1 = 1;
    }
}
```

```txt
ConstantPool {
    |002| CONSTANT_Methodref {Value='java/lang/Short.valueOf:(S)Ljava/lang/Short;', HexCode='0A00120013'}
    ......

code='04B800024CB1'
    0: iconst_1        // 04
    1: invokestatic 2  // B80002
    4: astore_1        // 4C
    5: return          // B1


LocalVariableTable:
index  start_pc  length  name_and_type
    0         0       6  this:Llsieun/sample/HelloWorld;
    1         5       1  short_1:Ljava/lang/Short;
```

### 9.4. char to Character

```java
public class HelloWorld {
    public void testSimple() {
        Character char_a = 'a';
    }
}
```

```txt
ConstantPool {
    |002| CONSTANT_Methodref {Value='java/lang/Character.valueOf:(C)Ljava/lang/Character;', HexCode='0A00120013'}
    ......

code='1061B800024CB1'
    0: bipush 97       // 1061
    2: invokestatic 2  // B80002
    5: astore_1        // 4C
    6: return          // B1


LocalVariableTable:
index  start_pc  length  name_and_type
    0         0       7  this:Llsieun/sample/HelloWorld;
    1         6       1  char_a:Ljava/lang/Character;
```

### 9.5. int to Integer

```java
public class HelloWorld {
    public void testSimple() {
        Integer int_62 = 62;
    }
}
```

```txt
ConstantPool {
    |002| CONSTANT_Methodref {Value='java/lang/Integer.valueOf:(I)Ljava/lang/Integer;', HexCode='0A00120013'}
    ......

code='103EB800024CB1'
    0: bipush 62       // 103E
    2: invokestatic 2  // B80002
    5: astore_1        // 4C
    6: return          // B1


LocalVariableTable:
index  start_pc  length  name_and_type
    0         0       7  this:Llsieun/sample/HelloWorld;
    1         6       1  int_62:Ljava/lang/Integer;
```

### 9.6. long to Long

```java
public class HelloWorld {
    public void testSimple() {
        Long long_618 = 618L; // 0.618是黄金分割点
    }
}
```

```txt
ConstantPool {
    |002| CONSTANT_Long {Value='618', HexCode='05000000000000026A'}
    |004| CONSTANT_Methodref {Value='java/lang/Long.valueOf:(J)Ljava/lang/Long;', HexCode='0A00140015'}
    ...

code='140002B800044CB1'
    0: ldc2_w 2        // 140002
    3: invokestatic 4  // B80004
    6: astore_1        // 4C
    7: return          // B1


LocalVariableTable:
index  start_pc  length  name_and_type
    0         0       8  this:Llsieun/sample/HelloWorld;
    1         7       1  long_618:Ljava/lang/Long;
```

The values of the integral types are integers in the following ranges:

- For `byte` , from `-128` to `127`, inclusive
- For `short` , from `-32768` to `32767`, inclusive
- For `int` , from `-2147483648` to `2147483647`, inclusive
- For `long` , from `-9223372036854775808` to `9223372036854775807`, inclusive
- For `char` , from '`\u0000`' to '`\uffff`' inclusive, that is, from `0` to `65535`

### 9.7. float to Float

```java
public class HelloWorld {
    public void testSimple() {
        Float float_pi = 3.14F;
    }
}
```

```txt
ConstantPool {
    |002| CONSTANT_Float {Value='3.14', HexCode='044048F5C3'}
    |003| CONSTANT_Methodref {Value='java/lang/Float.valueOf:(F)Ljava/lang/Float;', HexCode='0A00130014'}
    ......

code='1202B800034CB1'
    0: ldc 2           // 1202
    2: invokestatic 3  // B80003
    5: astore_1        // 4C
    6: return          // B1


LocalVariableTable:
index  start_pc  length  name_and_type
    0         0       7  this:Llsieun/sample/HelloWorld;
    1         6       1  float_pi:Ljava/lang/Float;
```

### 9.8. double to Double

```java
public class HelloWorld {
    public void testSimple() {
        Double double_e = 2.718;
    }
}
```

```txt
ConstantPool {
    |002| CONSTANT_Double {Value='2.718', HexCode='064005BE76C8B43958'}
    |004| CONSTANT_Methodref {Value='java/lang/Double.valueOf:(D)Ljava/lang/Double;', HexCode='0A00140015'}
    ......

code='140002B800044CB1'
    0: ldc2_w 2        // 140002
    3: invokestatic 4  // B80004
    6: astore_1        // 4C
    7: return          // B1

LocalVariableTable:
index  start_pc  length  name_and_type
    0         0       8  this:Llsieun/sample/HelloWorld;
    1         7       1  double_e:Ljava/lang/Double;
```

## 10. Unboxing Conversion

### 10.1. Boolean to boolean

```java
public class HelloWorld {
    public void testSimple() {
        boolean bool_true = Boolean.valueOf("TRUE");
    }
}
```

```txt
ConstantPool {
    |002| CONSTANT_String {Value='TRUE', HexCode='080014'}
    |003| CONSTANT_Methodref {Value='java/lang/Boolean.valueOf:(Ljava/lang/String;)Ljava/lang/Boolean;', HexCode='0A00150016'}
    |004| CONSTANT_Methodref {Value='java/lang/Boolean.booleanValue:()Z', HexCode='0A00150017'}
    ......

code='1202B80003B600043CB1'
    0: ldc 2           // 1202
    2: invokestatic 3  // B80003
    5: invokevirtual 4 // B60004
    8: istore_1        // 3C
    9: return          // B1


LocalVariableTable:
index  start_pc  length  name_and_type
    0         0      10  this:Llsieun/sample/HelloWorld;
    1         9       1  bool_true:Z
```

### 10.2. Integer to int

```java
public class HelloWorld {
    public void testSimple() {
        int int_value = Integer.valueOf("1024");
    }
}
```

```txt
ConstantPool {
    |002| CONSTANT_String {Value='1024', HexCode='080014'}
    |003| CONSTANT_Methodref {Value='java/lang/Integer.valueOf:(Ljava/lang/String;)Ljava/lang/Integer;', HexCode='0A00150016'}
    |004| CONSTANT_Methodref {Value='java/lang/Integer.intValue:()I', HexCode='0A00150017'}
    ......

code='1202B80003B600043CB1'
    0: ldc 2           // 1202
    2: invokestatic 3  // B80003
    5: invokevirtual 4 // B60004
    8: istore_1        // 3C
    9: return          // B1


LocalVariableTable:
index  start_pc  length  name_and_type
    0         0      10  this:Llsieun/sample/HelloWorld;
    1         9       1  int_value:I
```


